pi_base/__init__.py
pi_base/__main__.py
pi_base/_version.py
pi_base/make.py
pi_base/modpath.py
pi_base/net_rpi.cmd
pi_base/requirements-posix.txt
pi_base/requirements-win.txt
pi_base/requirements.txt
pi_base/upload.cmd
pi_base/upload.sh
pi_base/common/common_install.sh
pi_base/common/common_requirements.txt
pi_base/common/graphics/splash.pi-base.png
pi_base/common/graphics/splash.pi-base.svg
pi_base/common/pkg/boot/cmdline.txt.example
pi_base/common/pkg/boot/config.txt
pi_base/common/pkg/etc/boot.jpg
pi_base/common/pkg/etc/boot.wav
pi_base/common/pkg/etc/locale.gen
pi_base/common/pkg/etc/X11/xorg.conf.d/10-blanking.conf
pi_base/common/pkg/etc/default/keyboard
pi_base/common/pkg/etc/default/locale
pi_base/common/pkg/etc/lightdm/.keep
pi_base/common/pkg/etc/samba/smb.conf.example
pi_base/common/pkg/etc/systemd/system/app_manager_startup.service
pi_base/common/pkg/etc/systemd/system/hdmi-sound-rpi3.target
pi_base/common/pkg/etc/systemd/system/hdmi-sound-rpi4-c1.target
pi_base/common/pkg/etc/systemd/system/hdmi-sound-rpi4-c2.target
pi_base/common/pkg/etc/systemd/system/hdmi-sound.target
pi_base/common/pkg/etc/systemd/system/getty@tty1.service.d/.keep
pi_base/common/pkg/etc/udev/rules.d/60-watchdog.rules
pi_base/common/pkg/etc/wpa_supplicant/EXAMPLE_wpa_supplicant.conf
pi_base/common/pkg/home/pi/.bash_aliases
pi_base/common/pkg/home/pi/block_xxl.flf
pi_base/common/pkg/home/pi/.config/pulse/.keep
pi_base/common/pkg/home/pi/.ssh/authorized_keys
pi_base/common/pkg/usr/lib/systemd/system/.keep
pi_base/common/pkg/usr/local/bin/app_manager_startup
pi_base/common/pkg/usr/share/plymouth/themes/pix/pix.plymouth
pi_base/common/pkg/usr/share/plymouth/themes/pix/pix.script
pi_base/common/pkg/usr/share/plymouth/themes/pix/splash-power-off.png
pi_base/common/pkg/usr/share/plymouth/themes/pix/splash-power-on.png
pi_base/lib/app_utils.py
pi_base/lib/deploy_site.py
pi_base/lib/gd_service.py
pi_base/lib/large.py
pi_base/lib/large.txt
pi_base/lib/loggr.py
pi_base/lib/manager.py
pi_base-0.0.4.dist-info/AUTHORS.md
pi_base-0.0.4.dist-info/LICENSE
pi_base-0.0.4.dist-info/METADATA
pi_base-0.0.4.dist-info/WHEEL
pi_base-0.0.4.dist-info/entry_points.txt
pi_base-0.0.4.dist-info/top_level.txt
pi_base-0.0.4.dist-info/RECORD
