Metadata-Version: 2.1
Name: pi_base
Version: 0.0.4
Summary: Framework for creating Raspberry Pi appliances.
Author-email: Ilya Ivanchenko <iva2k@yahoo.com>
License: MIT License
Project-URL: Homepage, https://github.com/iva2k/pi-base
Project-URL: Repository, https://github.com/iva2k/pi-base
Project-URL: Issues, https://github.com/iva2k/pi-base/issues
Project-URL: Changelog, https://github.com/iva2k/pi-base/blob/main/CHANGELOG.md
Keywords: raspberry pi
Classifier: Development Status :: 3 - Alpha
Classifier: Intended Audience :: Developers
Classifier: Topic :: Software Development :: Build Tools
Classifier: Programming Language :: Python :: 3
Classifier: Programming Language :: Python :: 3 :: Only
Classifier: Programming Language :: Python :: 3.8
Classifier: Programming Language :: Python :: 3.9
Classifier: Programming Language :: Python :: 3.10
Classifier: Programming Language :: Python :: 3.11
Classifier: License :: OSI Approved :: MIT License
Classifier: Operating System :: OS Independent
Requires-Python: >=3.8
License-File: LICENSE
License-File: AUTHORS.md
Requires-Dist: pyyaml ~=6.0
Requires-Dist: pydrive2 ~=1.14.0
Provides-Extra: build
Requires-Dist: build[virtualenv] ==1.0.3 ; extra == 'build'
Provides-Extra: dev
Requires-Dist: pi-base[tox] ; extra == 'dev'
Requires-Dist: pi-base[version] ; extra == 'dev'
Requires-Dist: pi-base[format] ; extra == 'dev'
Requires-Dist: pi-base[lint] ; extra == 'dev'
Requires-Dist: pi-base[test] ; extra == 'dev'
Requires-Dist: pi-base[reports] ; extra == 'dev'
Requires-Dist: pi-base[doc] ; extra == 'dev'
Requires-Dist: pi-base[release] ; extra == 'dev'
Requires-Dist: pi-base[build] ; extra == 'dev'
Requires-Dist: esbonio ==0.16.4 ; extra == 'dev'
Requires-Dist: doc8 ==1.1.1 ; extra == 'dev'
Provides-Extra: doc
Requires-Dist: pi-base[version] ; extra == 'doc'
Requires-Dist: importlib-metadata ==7.0.1 ; extra == 'doc'
Requires-Dist: jinja2 ==3.1.2 ; extra == 'doc'
Requires-Dist: pip-licenses ==4.3.2 ; extra == 'doc'
Requires-Dist: sphinx ==7.2.6 ; extra == 'doc'
Requires-Dist: sphinx-autodoc-typehints ==1.24.0 ; extra == 'doc'
Requires-Dist: sphinx-book-theme ==1.1.2 ; extra == 'doc'
Requires-Dist: myst-parser ==2.0.0 ; extra == 'doc'
Provides-Extra: format
Requires-Dist: ruff ==0.2.1 ; extra == 'format'
Provides-Extra: lint
Requires-Dist: ruff ==0.2.1 ; extra == 'lint'
Requires-Dist: jinja2 ==3.1.2 ; extra == 'lint'
Requires-Dist: pyright ==1.1.352 ; extra == 'lint'
Requires-Dist: types-docutils ; extra == 'lint'
Requires-Dist: types-setuptools ; extra == 'lint'
Provides-Extra: release
Requires-Dist: pi-base[version] ; extra == 'release'
Provides-Extra: reports
Requires-Dist: coverage[toml] ==7.3.1 ; extra == 'reports'
Requires-Dist: junitparser ==3.1.2 ; extra == 'reports'
Provides-Extra: test
Requires-Dist: pytest ==7.4.1 ; extra == 'test'
Requires-Dist: pytest-randomly ==3.15.0 ; extra == 'test'
Requires-Dist: pytest-cov ==4.1.0 ; extra == 'test'
Provides-Extra: tox
Requires-Dist: tox ==4.13.0 ; extra == 'tox'
Provides-Extra: version
Requires-Dist: zest-releaser ==9.1.3 ; extra == 'version'
